ndtools/__init__.py
ndtools/py.typed
ndtools/comparison/__init__.py
ndtools/comparison/builtins.py
ndtools/comparison/comparables.py
ndtools/comparison/operators.py
ndtools/comparison/utils.py
ndtools-1.0.1.dist-info/METADATA
ndtools-1.0.1.dist-info/WHEEL
ndtools-1.0.1.dist-info/licenses/LICENSE
ndtools-1.0.1.dist-info/RECORD
