Metadata-Version: 2.4
Name: ndtools
Version: 1.0.1
Summary: Collection of tools to extend multidimensional array operations
Project-URL: homepage, https://astropenguin.github.io/ndtools/v1.0.1
Project-URL: repository, https://github.com/astropenguin/ndtools
Author-email: Akio Taniguchi <taniguchi.akio@gmail.com>
License: MIT License
License-File: LICENSE
Keywords: comparison,duck-array,ndarray
Classifier: License :: OSI Approved :: MIT License
Classifier: Programming Language :: Python :: 3
Classifier: Programming Language :: Python :: 3.9
Classifier: Programming Language :: Python :: 3.10
Classifier: Programming Language :: Python :: 3.11
Classifier: Programming Language :: Python :: 3.12
Classifier: Programming Language :: Python :: 3.13
Requires-Python: <3.14,>=3.9
Requires-Dist: numpy<3.0,>=1.23
Requires-Dist: pandas-stubs<3.0,>=1.4
Requires-Dist: pandas<3.0,>=1.4
Requires-Dist: typing-extensions<5.0,>=4.0
